README.md
setup.cfg
setup.py
TOPSIS_Dipti_101803601/__init__.py
TOPSIS_Dipti_101803601/topsis.py
TOPSIS_Dipti_101803601.egg-info/PKG-INFO
TOPSIS_Dipti_101803601.egg-info/SOURCES.txt
TOPSIS_Dipti_101803601.egg-info/dependency_links.txt
TOPSIS_Dipti_101803601.egg-info/requires.txt
TOPSIS_Dipti_101803601.egg-info/top_level.txt