Metadata-Version: 2.1
Name: TOPSIS-Dipti-101803601
Version: 0.1
Summary: Pyhon Package for TOPSIS score
Home-page: https://github.com/diptikaushal/TOPSIS-Dipti-101803601
Author: Dipti
Author-email: dkaushal_be18@thapar.edu
License: MIT
Platform: UNKNOWN
Classifier: Development Status :: 3 - Alpha
Classifier: Intended Audience :: Developers
Classifier: License :: OSI Approved :: MIT License
Classifier: Programming Language :: Python :: 3.4
Classifier: Programming Language :: Python :: 3.5
Classifier: Programming Language :: Python :: 3.6
Classifier: Programming Language :: Python :: 3.7
Classifier: Programming Language :: Python :: 3.8
